pyw/__init__.py
pyw_music-0.0.0.post1.dist-info/METADATA
pyw_music-0.0.0.post1.dist-info/WHEEL
pyw_music-0.0.0.post1.dist-info/licenses/LICENSE
pyw_music-0.0.0.post1.dist-info/RECORD
