Metadata-Version: 2.4
Name: pyw-music
Version: 0.0.0.post1
Summary: Music processing bundle (music21 + musicparser)
Project-URL: Homepage, https://github.com/pythonWoods/pyw-music
Project-URL: Documentation, https://pythonwoods.dev/docs/pyw-music/latest/
Project-URL: Issues, https://github.com/pythonWoods/pyw-music/issues
Project-URL: Changelog, https://github.com/pythonWoods/pyw-music/releases
Author: pythonWoods
License: MIT
License-File: LICENSE
Classifier: Development Status :: 2 - Pre-Alpha
Classifier: License :: OSI Approved :: MIT License
Classifier: Programming Language :: Python :: 3 :: Only
Classifier: Programming Language :: Python :: 3.11
Classifier: Typing :: Typed
Requires-Python: >=3.9
Requires-Dist: pyw-core>=0.0.0
Requires-Dist: pyw-music21>=0.0.0
Requires-Dist: pyw-musicparser>=0.0.0
